uid2_client/__init__.py
uid2_client/advertising_token_version.py
uid2_client/auto_refresh.py
uid2_client/bidstream_client.py
uid2_client/client.py
uid2_client/client_type.py
uid2_client/decryption_status.py
uid2_client/encryption.py
uid2_client/encryption_data_response.py
uid2_client/encryption_status.py
uid2_client/envelope.py
uid2_client/euid_client_factory.py
uid2_client/identity_buckets_response.py
uid2_client/identity_map_client.py
uid2_client/identity_map_input.py
uid2_client/identity_map_response.py
uid2_client/identity_map_v3_client.py
uid2_client/identity_map_v3_input.py
uid2_client/identity_map_v3_response.py
uid2_client/identity_scope.py
uid2_client/identity_tokens.py
uid2_client/identity_type.py
uid2_client/input_util.py
uid2_client/keys.py
uid2_client/publisher_client.py
uid2_client/refresh_keys_util.py
uid2_client/refresh_response.py
uid2_client/request_response_util.py
uid2_client/sharing_client.py
uid2_client/token_generate_input.py
uid2_client/token_generate_response.py
uid2_client/token_refresh_response.py
uid2_client/uid2_base64_url_coder.py
uid2_client/uid2_client_factory.py
uid2_client/uid2_response.py
uid2_client/uid2_token_generator.py
uid2_client/unmapped_identity_reason.py
uid2_client-2.8.0.dist-info/licenses/LICENSE
uid2_client-2.8.0.dist-info/METADATA
uid2_client-2.8.0.dist-info/WHEEL
uid2_client-2.8.0.dist-info/top_level.txt
uid2_client-2.8.0.dist-info/RECORD
