Metadata-Version: 2.4
Name: uid2_client
Version: 2.8.0
Summary: UID2 SDK for Python
Author-email: UID2 team <unifiedid-admin@thetradedesk.com>
License:                                  Apache License
Project-URL: Homepage, https://github.com/IABTechLab/uid2-client-python
Project-URL: Bug Tracker, https://github.com/IABTechLab/uid2-client-python/issues
Classifier: Programming Language :: Python :: 3
Classifier: License :: OSI Approved :: MIT License
Classifier: Operating System :: OS Independent
Requires-Python: >=3.8
License-File: LICENSE
Requires-Dist: pycryptodome
Requires-Dist: bitarray
Provides-Extra: dev
Requires-Dist: pytest; extra == "dev"
Requires-Dist: pytest-cov; extra == "dev"
Requires-Dist: unittest-xml-reporting; extra == "dev"
Provides-Extra: keywords
Requires-Dist: uid2; extra == "keywords"
Requires-Dist: euid; extra == "keywords"
Dynamic: license-file
